CHANGES.txt
MANIFEST.in
README.rst
requirements.cfg
setup.cfg
setup.py
src/FilesOperationLibrary/__init__.py
src/FilesOperationLibrary/exception.py
src/FilesOperationLibrary/handle_bin.py
src/FilesOperationLibrary/handle_csv.py
src/FilesOperationLibrary/handle_ftp.py
src/FilesOperationLibrary/handle_log.py
src/FilesOperationLibrary/handle_txt.py
src/FilesOperationLibrary/handle_xls.py
src/FilesOperationLibrary/handle_xml.py
src/FilesOperationLibrary/interface.py
src/FilesOperationLibrary/store.py
src/FilesOperationLibrary/unzip_file.py
src/FilesOperationLibrary.egg-info/PKG-INFO
src/FilesOperationLibrary.egg-info/SOURCES.txt
src/FilesOperationLibrary.egg-info/dependency_links.txt
src/FilesOperationLibrary.egg-info/requires.txt
src/FilesOperationLibrary.egg-info/top_level.txt