Metadata-Version: 1.1
Name: FilesOperationLibrary
Version: 1.0.0
Summary: Robot Framework test library Files Operation
Home-page: https://github.com
Author: leo
Author-email: liyaowang518@gmail.com
License: Apache License 2.0
Keywords: robotframework testing testautomation Files Operation
Platform: any
Classifier: Development Status :: 5 - Production/Stable
Classifier: License :: OSI Approved :: Apache Software License
Classifier: Operating System :: OS Independent
Classifier: Programming Language :: Python
Classifier: Programming Language :: Python :: 2.7
Classifier: Topic :: Software Development :: Testing
Classifier: Framework :: Robot Framework
Classifier: Framework :: Robot Framework :: Library
